dqrobotics/interfaces/coppeliasim/__init__.py
dqrobotics/interfaces/coppeliasim/_core.cpython-313-x86_64-linux-gnu.so
dqrobotics_interface_coppeliasim_zmq-25.4.0a19.dist-info/licenses/LICENSE
dqrobotics_interface_coppeliasim_zmq-25.4.0a19.dist-info/METADATA
dqrobotics_interface_coppeliasim_zmq-25.4.0a19.dist-info/WHEEL
dqrobotics_interface_coppeliasim_zmq-25.4.0a19.dist-info/top_level.txt
dqrobotics_interface_coppeliasim_zmq-25.4.0a19.dist-info/RECORD
