Metadata-Version: 2.1
Name: dqrobotics-interface-coppeliasim-zmq
Version: 25.4.0a19
Summary: dqrobotics Python interface for CoppeliaSim ZMQ
Author-email: "Murilo M. Marinho" <murilomarinho@ieee.org>
Maintainer-email: "Murilo M. Marinho" <murilomarinho@ieee.org>
Project-URL: Homepage, https://dqrobotics.github.io
Project-URL: Documentation, https://dqroboticsgithubio.readthedocs.io/en/latest/installation/python.html
Project-URL: Repository, https://github.com/dqrobotics/python
Project-URL: Issues, https://github.com/dqrobotics/python/issues
Classifier: Programming Language :: Python :: 3.10
Classifier: Programming Language :: Python :: 3.11
Classifier: Programming Language :: Python :: 3.12
Classifier: Programming Language :: Python :: 3.13
Classifier: Programming Language :: C++
Classifier: Development Status :: 5 - Production/Stable
Classifier: Operating System :: POSIX :: Linux
Classifier: License :: OSI Approved :: GNU Lesser General Public License v3 or later (LGPLv3+)
Requires-Python: >=3.9
License-File: LICENSE
Requires-Dist: dqrobotics
